open_klant_client-0.4.0.dist-info/licenses/LICENSE.md
openklant_client/__init__.py
openklant_client/client.py
openklant_client/exceptions.py
openklant_client/_methods/__init__.py
openklant_client/_methods/maak_klant_contact.py
openklant_client/_resources/__init__.py
openklant_client/_resources/actor.py
openklant_client/_resources/base.py
openklant_client/_resources/betrokkene.py
openklant_client/_resources/digitaal_adres.py
openklant_client/_resources/interne_taak.py
openklant_client/_resources/klant_contact.py
openklant_client/_resources/onderwerp_object.py
openklant_client/_resources/partij.py
openklant_client/_resources/partij_identificator.py
openklant_client/types/__init__.py
openklant_client/types/common.py
openklant_client/types/error.py
openklant_client/types/iso_639_2.py
openklant_client/types/pagination.py
openklant_client/types/methods/__init__.py
openklant_client/types/methods/maak_klant_contact.py
openklant_client/types/resources/__init__.py
openklant_client/types/resources/actor.py
openklant_client/types/resources/betrokkene.py
openklant_client/types/resources/digitaal_adres.py
openklant_client/types/resources/interne_taak.py
openklant_client/types/resources/klant_contact.py
openklant_client/types/resources/onderwerp_object.py
openklant_client/types/resources/partij.py
openklant_client/types/resources/partij_identificator.py
open_klant_client-0.4.0.dist-info/METADATA
open_klant_client-0.4.0.dist-info/WHEEL
open_klant_client-0.4.0.dist-info/top_level.txt
open_klant_client-0.4.0.dist-info/RECORD
