Metadata-Version: 2.4
Name: open-klant-client
Version: 0.4.0
Summary: API Client library to communicate with the Open Klant service.
Author-email: Maykin Media <support@maykinmedia.nl>
License-Expression: EUPL-1.2
Project-URL: Homepage, https://github.com/maykinmedia/open-klant-client
Project-URL: Documentation, http://maykin-open-klant-client.readthedocs.io/en/latest/
Project-URL: Bug Tracker, https://github.com/maykinmedia/open-klant-client/issues
Project-URL: Source Code, https://github.com/maykinmedia/open-klant-client
Keywords: maykin,openklant,open klant,klantinteracties,common ground,api client
Classifier: Development Status :: 3 - Alpha
Classifier: Intended Audience :: Developers
Classifier: Operating System :: Unix
Classifier: Operating System :: MacOS
Classifier: Operating System :: Microsoft :: Windows
Classifier: Programming Language :: Python :: 3.12
Classifier: Programming Language :: Python :: 3.13
Classifier: Topic :: Software Development :: Libraries :: Python Modules
Requires-Python: >=3.12
License-File: LICENSE.md
Requires-Dist: ape_pie>=0.2.0
Provides-Extra: tests
Requires-Dist: pytest; extra == "tests"
Requires-Dist: tox; extra == "tests"
Requires-Dist: ruff; extra == "tests"
Requires-Dist: pyright; extra == "tests"
Requires-Dist: vcrpy; extra == "tests"
Requires-Dist: pydantic; extra == "tests"
Requires-Dist: pytest-recording; extra == "tests"
Requires-Dist: requests; extra == "tests"
Requires-Dist: types-requests; extra == "tests"
Requires-Dist: factory-boy; extra == "tests"
Provides-Extra: docs
Requires-Dist: sphinx; extra == "docs"
Requires-Dist: sphinx-rtd-theme; extra == "docs"
Provides-Extra: release
Requires-Dist: bump-my-version; extra == "release"
Dynamic: license-file
